<?xml version="1.0" encoding="utf-8"?>
<doctrine-mapping xmlns="http://doctrine-project.org/schemas/orm/doctrine-mapping" xmlns:xsi="http://www.w3.org/2001/XMLSchema-instance" xsi:schemaLocation="http://doctrine-project.org/schemas/orm/doctrine-mapping http://doctrine-project.org/schemas/orm/doctrine-mapping.xsd">
  <entity name="Suiviprojet\AdministrateurBundle\Entity\Equipe" table="equipe">
    <id name="idequipe" type="integer" column="idEquipe">
      <generator strategy="IDENTITY"/>
    </id>
    <field name="nom" type="string" column="nom" length="45" precision="0" scale="0" nullable="false"/>
    <field name="nbdifficulte" type="integer" column="nbDifficulte" precision="0" scale="0" nullable="false"/>
    <many-to-many field="developperdevelopper" target-entity="Suiviprojet\AdministrateurBundle\Entity\Developper" inversed-by="equipeequipe">
      <join-table name="equipe_has_developper">
        <join-columns>
          <join-column name="equipe_idEquipe" referenced-column-name="idEquipe"/>
        </join-columns>
        <inverse-join-columns>
          <join-column name="developper_idDevelopper" referenced-column-name="idDevelopper" nullable="1"/>
        </inverse-join-columns>
      </join-table>
    </many-to-many>
  </entity>
</doctrine-mapping>
